{
	"Abakan": "Абакан",
	"Abidjan": "Абиджан",
	"Abu Dhabi": "Абу-Даби",
	"Abuja": "Абуйя",
	"Accra": "Аккра",
	"Addis Ababa": "Аддис-Абеба",
	"Adelaide": "Аделаида",
	"Afghanistan": "Афганистан",
	"Afghanistan Time": "Афганистан Время",
	"Alaska": "Аляска",
	"Alaska Standard Time": "Стандартное время на Аляске",
	"Albania": "Албания",
	"Algeria": "Алжир",
	"Algiers": "Алжир",
	"Alma-Ata Time": "Алма-Ата Время",
	"Amazon Standard Time": "Amazon Поясному Времени",
	"Amazon Time (Brazil)": "Amazon Время (Бразилия)",
	"Amman": "Амман",
	"Amsterdam": "Амстердам",
	"Anadyr": "Анадырь",
	"Anadyr Time": "Анадырь Время",
	"Anchorage": "Анкоридж",
	"Andorra": "Андорра",
	"Andorra la Vella": "Андорра-ла-Велья",
	"Angola": "Ангола",
	"Ankara": "Анкара",
	"Antananarivo": "Антананариву",
	"Antigua & Barbuda": "Антигуа и Барбуда",
	"Apia": "Апия",
	"Aqtau Time": "Актау Время",
	"Aqtobe Time": "Актюбинская Время",
	"Arabia Standard Time": "Аравия Стандартное Время",
	"Araguaina": "Арагуаяна",
	"Argentina": "Аргентина",
	"Argentina Time": "Аргентина Время",
	"Arizona": "Аризона",
	"Arkhangelsk": "Архангельск",
	"Armenia": "Армения",
	"Armenia Time": "Армения Время",
	"Aruba": "Аруба",
	"ASEAN Common Time": "Асеан Общие Времени",
	"Ashkhabad": "Ашхабад",
	"Asmara": "Асмара",
	"Astana": "Астана",
	"Astrakhan": "Астрахань",
	"Asuncion": "Асунсьон",
	"Athens": "Афины",
	"Atlanta": "Атланта",
	"Atlantic Standard Time": "Атлантическое время",
	"Auckland": "Окленд",
	"Australia": "Австралия",
	"Austria": "Австрия",
	"Azerbaijan": "Азербайджан",
	"Azerbaijan Time": "Азербайджан Время",
	"Azores": "Азорские о-ва",
	"Azores Time": "Азорские Время",
	"Baghdad": "Багдад",
	"Bahamas": "Багамские острова",
	"Bahia": "Баия",
	"Bahrain": "Бахрейн",
	"Baku": "Баку",
	"Bali": "Бали",
	"Bamako": "Бамако",
	"Bandar Seri Begawan": "Бандар-Сери-Бегаван",
	"Bangalore": "Бангалор",
	"Bangkok": "Бангкок",
	"Bangladesh": "Бангладеш",
	"Bangladesh Time": "Бангладеш Время",
	"Bangui": "Банги",
	"Banjul": "Банджул",
	"Barbados": "Барбадос",
	"Barcelona": "Барселона",
	"Barnaul": "Барнаул",
	"Beijing": "Пекин",
	"Beirut": "Бейрут",
	"Belarus": "Белоруссия",
	"Belem": "Белен",
	"Belgium": "Бельгия",
	"Belgorod": "Белгород",
	"Belize": "Белиз",
	"Belmopan": "Бельмопан",
	"Benin": "Бенин",
	"Beograd": "Белград",
	"Berlin": "Берлин",
	"Bermuda": "Бермудские о-ва",
	"Bern": "Берн",
	"Bhutan": "Бутан",
	"Bhutan Time": "Бутан Время",
	"Birobidzhan": "Биробиджан",
	"Bishkek": "Бишкек",
	"Bissau": "Бисау",
	"Blagoveschensk": "Благовещенск",
	"Boa Vista": "Боа-Виста",
	"Bogota": "Богота",
	"Boise": "Бойсе",
	"Bolivia": "Боливия",
	"Bolivia Time": "Боливия Время",
	"Bosnia & Herzegovina": "Босния и Герцеговина",
	"Boston": "Бостон",
	"Botswana": "Ботсвана",
	"Brasilia": "Бразилия",
	"Brasilia Time": "Бразилиа Время",
	"Bratislava": "Братислава",
	"Bratsk": "Братск",
	"Brazil": "Бразилия",
	"Brazil Time": "Бразилия Время",
	"Brazzaville": "Браззавиль",
	"Bridgetown": "Бриджтаун",
	"Brisbane": "Брисбен",
	"Britain (UK)": "Великобритания",
	"Brunei": "Бруней",
	"Brunei Time": "Бруней Время",
	"Brussels": "Брюссель",
	"Bucharest": "Бухарест",
	"Budapest": "Будапешт",
	"Buenos Aires": "Буэнос-Айрес",
	"Bujumbura": "Бужумбура",
	"Bulgaria": "Болгария",
	"Burkina Faso": "Буркина-Фасо",
	"Burundi": "Бурунди",
	"Cairo": "Каир",
	"Calgary": "Калгари",
	"Cambodia": "Камбоджа",
	"Cameroon": "Камерун",
	"Campo Grande": "Кампу-Гранди",
	"Canada": "Канада",
	"Canberra": "Канберра",
	"Cape Town": "Кейптаун",
	"Cape Verde": "Кабо-Верде",
	"Cape Verde Time": "Кабо-Верде Время",
	"Caracas": "Каракас",
	"Casablanca": "Касабланка",
	"Central African Rep.": "Центральноафриканская Республика",
	"Central African Time": "Центральный Время Африки",
	"Central European Time": "Central European Time",
	"Central Standard Time": "Центральное Время",
	"Central Standard Time (North America)": "Центральное Время (Северная Америка)",
	"Central Standard Time (Northern Territory)": "Северная Территория",
	"Central Standard Time (South Australia)": "Центральное Время (Южная Австралия)",
	"Central Standard Time (South Australia/New South Wales)": "Новый Южный Уэльс",
	"Central Western Standard Time (Australia) unofficial": "Центральный Западная Поясному Времени (Австралия) Неофициальный",
	"Chad": "Чад",
	"Chamorro Standard Time": "Чаморро Поясному Времени",
	"Chatham Standard Time": "Chatham Standard Time",
	"Cheboksary": "Чебоксары",
	"Chelyabinsk": "Челябинск",
	"Cherkessk": "Черкесск",
	"Chiang Mai": "Чианг-Май",
	"Chicago": "Чикаго",
	"Chihuahua": "Чиуауа",
	"Chile": "Чили",
	"Chile Time": "Чили Время",
	"China": "Китай",
	"China Standard Time": "Китай Поясному Времени",
	"Chita": "Чита",
	"Chittagong": "Читтагонг",
	"Choibalsan": "Чойбалсан",
	"Christmas": "Рождество",
	"Christmas Island": "Остров Рождества",
	"Christmas Island Time": "Остров Рождества Время",
	"Chuuk": "Чуук",
	"Chuuk Time": "Chuuk Время",
	"Cocos Islands Time": "Кокосовые Острова Время",
	"Colombia": "Колумбия",
	"Colombia Time": "Колумбия Время",
	"Colombo": "Коломбо",
	"Comoros": "Коморские острова",
	"Conakry": "Конакри",
	"Congo (Dem. Rep.)": "Конго (Дем. Респ.)",
	"Congo (Rep.)": "Конго (Респ.)",
	"Copenhagen": "Копенгаген",
	"Costa Rica": "Коста-Рика",
	"Cote d'Ivoire": "Cote d'Ivoire",
	"Croatia": "Хорватия",
	"Cuba": "Куба",
	"Cuiaba": "Куяба",
	"Cyprus": "Кипр",
	"Czech Republic": "Чехия",
	"Dakar": "Дакар",
	"Dallas": "Даллас",
	"Damascus": "Дамасск",
	"Danmarkshavn": "Датская гавань",
	"Dar es Salaam": "Дар-Эс-Салам",
	"Darwin": "Дарвин",
	"Dawson": "Доусон",
	"Denmark": "Дания",
	"Denver": "Денвер",
	"Detroit": "Детройт",
	"Dhaka": "Дакка",
	"Djibouti": "Джибути",
	"Doha": "Доха",
	"Dominican Republic": "Доминиканская Республика",
	"Dubai": "Дубаи",
	"Dublin": "Дублин",
	"Dudinka": "Дудинка",
	"Dushanbe": "Душанбе",
	"East Africa Time": "Восточная Африка Время",
	"Easter Is. Time": "Пасха. Время",
	"Eastern African Time": "Восточной Африки Время",
	"Eastern European Time": "Восточноевропейское Время",
	"Eastern Greenland Time": "Восточная Гренландия Время",
	"Eastern Standard Time": "Eastern Standard Time",
	"Eastern Standard Time (Australia)": "Eastern Standard Time (Австралия)",
	"Eastern Standard Time (New South Wales)": "Новый Южный Уэльс",
	"Eastern Standard Time (North America)": "Eastern Standard Time (Северная Америка)",
	"Eastern Standard Time (Queensland)": "Квинсленд",
	"Eastern Standard Time (Tasmania)": "Тасмания",
	"Ecuador": "Эквадор",
	"Ecuador Time": "Эквадор Время",
	"Edinburgh": "Эдинбург",
	"Edmonton": "Edmonton",
	"Egypt": "Египет",
	"Eirunepe": "Эйрунепе",
	"Ekaterinburg": "Екатеринбург",
	"Elista": "Элиста",
	"El Salvador": "Эль-Сальвадор",
	"Equatorial Guinea": "Экваториальная Гвинея",
	"Eritrea": "Эритрея",
	"Estonia": "Эстония",
	"Ethiopia": "Эфиопия",
	"Eucla": "Еукла",
	"Fernando de Noronha Time": "Фернандо Де Норонья Время",
	"Fiji": "Фиджи",
	"Fiji Time": "Фиджи Время",
	"Finland": "Финляндия",
	"Fortaleza": "Форталеза",
	"France": "Франция",
	"Frankfurt": "Франкфурт",
	"Freetown": "Фритаун",
	"Funafuti": "Фунафути",
	"Gabon": "Габон",
	"Gaborone": "Габороне",
	"Galapagos": "Галапагос",
	"Galapagos Time": "Галапагосские Время",
	"Gambia": "Гамбия",
	"Gambier Time": "Гамбиер Время",
	"Georgetown": "Джорджтаун",
	"Georgia": "Грузия",
	"Georgia Time": "Грузия Время",
	"Germany": "Германия",
	"Ghana": "Гана",
	"Gilbert Is. Time": "Гилберт. Время",
	"Glace Bay": "Глейс-Бей",
	"Gorno-Altaysk": "Горно-Алтайск",
	"Greece": "Греция",
	"Greenland": "Гренландия",
	"Greenwich Mean Time": "Время по Гринвичу",
	"Grenada": "Гренада",
	"Grozny": "Грозный",
	"Guam": "Гуам",
	"Guangzhou": "Гуанчжоу",
	"Guatemala": "Гватемала",
	"Guatemala City": "Гватемала",
	"Guayaquil": "Гуаякиль",
	"Guinea": "Гвинея",
	"Guinea-Bissau": "Гвинея Бисау",
	"Gulf Standard Time": "Gulf Стандартное Время",
	"Guyana": "Гайана",
	"Guyana Time": "Гайана Время",
	"Haiti": "Гаити",
	"Halifax": "Галифакс",
	"Hamburg": "Hamburg",
	"Hamilton": "Гамильтон",
	"Hanoi": "Ханой",
	"Harare": "Хараре",
	"Hawaii": "Гавайи",
	"Hawaii-Aleutian Standard Time": "Гавайи-Алеутской Поясному Времени",
	"Hawaii Standard Time": "Гавайи Поясному Времени",
	"Helsinki": "Хельсинки",
	"Hobart": "Хобарт",
	"Ho Chi Minh City": "Хошимин",
	"Honduras": "Гондурас",
	"Hong Kong": "Гонконг",
	"Hong Kong Time": "Время в Гонконге",
	"Honiara": "Хониара",
	"Honolulu": "Гонолулу",
	"Houston": "Хьюстон",
	"Hovd": "Ховд",
	"Hungary": "Венгрия",
	"Iceland": "Исландия",
	"India": "Индия",
	"Indian Standard Time": "Индийский Поясному Времени",
	"Indochina Time": "Индокитай Время",
	"Indonesia": "Индонезия",
	"Ioshkar Ola": "Йошкар-Ола",
	"Iran": "Иран",
	"Iran Time": "Иран Время",
	"Iraq": "Ирак",
	"Ireland": "Ирландия",
	"Irkutsk": "Иркутск",
	"Irkutsk Time": "Иркутск Время",
	"Islamabad": "Исламабад",
	"Israel": "Израиль",
	"Israel Standard Time": "Израильское Время",
	"Istanbul": "Стамбул",
	"Italy": "Италия",
	"Ivanovo": "Иваново",
	"Izhevsk": "Ижевск",
	"Jakarta": "Джакарта",
	"Jamaica": "Ямайка",
	"James Town": "Джеймстаун",
	"Japan": "Япония",
	"Japan Standard Time": "Япония Поясному Времени",
	"Java Time": "Java Время",
	"Jayapura": "Яяпура",
	"Jayapura Time": "Джаяпура Время",
	"Jeddah": "Джедда",
	"Jerusalem": "Иерусалим",
	"Johannesburg": "Йоханнесбург",
	"Jordan": "Иордания",
	"Juneau": "Джуно",
	"Kabul": "Кабул",
	"Kaliningrad": "Калининград",
	"Kaluga": "Калуга",
	"Kampala": "Кампала",
	"Karachi": "Карачи",
	"Kathmandu": "Катманду",
	"Kazakhstan": "Казахстан",
	"Kazan": "Казань",
	"Kemerovo": "Кемерово",
	"Kenya": "Кения",
	"Khartoum": "Хартум",
	"Khovd Time": "Khovd Время",
	"Kiev": "Киев",
	"Kigali": "Кигали",
	"Kingston": "Кингстон",
	"Kinshasa": "Киншаса",
	"Kirgizstan Time": "Кыргызстан Время",
	"Kiribati": "Кирибати",
	"kirov": "Киров",
	"Kishinev": "Кишинев",
	"Komsomolsk-on-Amur": "Комсомольск-на-Амуре",
	"Korea (North)": "Корея (Северная)",
	"Korea (South)": "Корея (Южная)",
	"Korea Standard Time": "Корея Поясному Времени",
	"Koror": "Корор",
	"Kosrae Time": "Kosrae Время",
	"Krasnodar": "Краснодар",
	"Krasnoyarsk": "Красноярск",
	"Krasnoyarsk Time": "Красноярск Время",
	"Kualalumpur": "Куала-Лумпур",
	"Kurgan": "Курган",
	"Kursk": "Курск",
	"Kuwait": "Кувейт",
	"Kuwait City": "Кувейт",
	"Kyrgyzstan": "Киргизия",
	"Kyzyl": "Кызыл",
	"La Habana": "Гавана",
	"Laos": "Лаос",
	"La Paz": "Ла-Пас",
	"Las Vegas": "Лас-Вегас",
	"Latvia": "Латвия",
	"Lebanon": "Ливан",
	"Lesotho": "Лесото",
	"Liberia": "Либерия",
	"Libreville": "Либрвиль",
	"Libya": "Ливия",
	"Liechtenstein": "Лихтенштейн",
	"Lilongwe": "Лилонгве",
	"Lima": "Лима",
	"Line Is. Time": "Линия. Время",
	"Lisbon": "Лиссабон",
	"Lithuania": "Литва",
	"Ljubljana": "Любляна",
	"Load Howe Standard Time": "Загрузите Хау Стандартное Время",
	"Lome": "Ломе",
	"London": "Лондон",
	"Los Angeles": "Лос-Анджелес",
	"Luanda": "Луанда",
	"Lusaka": "Лусака",
	"Luxembourg": "Люксембург",
	"Luxemburg": "Люксембург",
	"Luzon": "Лусон",
	"Macao": "Макао",
	"Macau": "Macau",
	"Macedonia": "Македония",
	"Macquarie Island Station Time": "Остров Маккуори Станция Время",
	"Madagascar": "Мадагаскар",
	"Madrid": "Мадрид",
	"Magadan": "Магадан",
	"Magadan Time": "Магадан Время",
	"Majuro": "Маджуро",
	"Makassar": "Макасар",
	"Malabo": "Малабо",
	"Malawi": "Малави",
	"Malaysia": "Малайзия",
	"Malaysia Time": "Малайзия Время",
	"Maldives": "Мальдивы",
	"Maldives Time": "Мальдивские О-Ва Время",
	"Male": "Мале",
	"Mali": "Мали",
	"Malta": "Мальта",
	"Managua": "Манагуа",
	"Manama": "Манама",
	"Manaus": "Манаус",
	"Mandalay": "Мандалай",
	"Manila": "Манила",
	"Maputo": "Мапуто",
	"Marquesas Time": "Маркизские Время",
	"Marshall Islands": "Маршалловы о-ва",
	"Marshall Islands Time": "Маршалловы Острова Время",
	"Maseru": "Масеру",
	"Mauritania": "Мавритания",
	"Mauritius": "Маврикий",
	"Mauritius Time": "Маврикий Время",
	"Mbabane": "Мбабане",
	"Melbourne": "Мельбурн",
	"Menominee": "Меномини",
	"MeST": "MeST",
	"Mexico": "Мексика",
	"Mexico City": "Мехико",
	"Micronesia": "Микронезия",
	"Milano": "Милан",
	"Minsk": "Минск",
	"Mogadishu": "Могадишу",
	"Moldova": "Молдова",
	"Monaco": "Монако",
	"Mongolia": "Монголия",
	"Monrovia": "Монровия",
	"Montenegro": "Черногория",
	"Montevideo": "Монтевидео",
	"Montreal": "Монреаль",
	"Morocco": "Марокко",
	"Moroni": "Морони",
	"Moscow": "Москва",
	"Moscow Standard Time": "Москва Поясному Времени",
	"Mountain Standard Time": "Горное Время",
	"Mountain Standard Time (North America)": "Горное Время (Северная Америка)",
	"Mozambique": "Мозамбик",
	"Mumbai": "Мумбаи",
	"Munich": "Мюнхен",
	"Murmansk": "Мурманск",
	"Muscat": "Мускат",
	"Myanmar (Burma)": "Мьянма (Бирма)",
	"Myanmar Time": "Мьянма Время",
	"Nairobi": "Найроби",
	"Nalchik": "Нальчик",
	"Namibia": "Намибия",
	"Napoli": "Неаполь",
	"Naryan-Mar": "Нарьян-Мар",
	"Nassau": "Нассау",
	"Nauru": "Науру",
	"Nauru Time": "Науру Время",
	"N'Djamena": "Нджамена",
	"Nepal": "Непал",
	"Nepal Time": "Непал Время",
	"Netherlands": "Нидерланды",
	"New Caledonia": "Новая Каледония",
	"New Caledonia Time": "Новая Каледония Время",
	"New Delhi": "Дели",
	"Newfoundland Standard Time": "Ньюфаундленд Поясному Времени",
	"New York": "Нью-Йорк",
	"New Zealand": "Новая Зеландия",
	"New Zealand Standard Time": "Новая Зеландия Поясному Времени",
	"Niamey": "Ниамей",
	"Nicaragua": "Никарагуа",
	"Nicosia": "Никосия",
	"Niger": "Нигер",
	"Nigeria": "Нигерия",
	"Nizhni Novgorod": "Нижний Новгород",
	"Norfolk Island": "Остров Норфолк",
	"Norfolk Time": "Норфолк Время",
	"Norilsk": "Норильск",
	"Norway": "Норвегия",
	"Nouakchott": "Нуакшот",
	"Novgorod": "Новгород",
	"Novokuznetsk": "Новокузнецк",
	"Novosibirsk": "Новосибирск",
	"Novosibirsk Time": "Новосибирск Время",
	"Nukualofa": "Нукуалофа",
	"Oman": "Оман",
	"Omsk": "Омск",
	"Omsk Time": "Омск Время",
	"Oral Time": "Время Оральный",
	"Oranjestad": "Ораньестад",
	"Orel": "Орел",
	"Orenburg": "Оренбург",
	"Osaka": "Osaka",
	"Oslo": "Осло",
	"Ottawa": "Оттава",
	"Ouagadougou": "Уагадугу",
	"Pacific Standard Time": "Стандартное тихоокеанское время",
	"Pacific Standard Time (North America)": "Стандартное тихоокеанское время (Северная Америка)",
	"Pakistan": "Пакистан",
	"Pakistan Time": "Пакистан Время",
	"Palau": "Палау",
	"Palau Time": "Palau Время",
	"Palestine": "Палестина",
	"Palikir": "Паликир",
	"Panama": "Панама",
	"Panama City": "Панама",
	"Papua": "Папуа",
	"Papua New Guinea": "Папуа - Новая Гвинея",
	"Papua New Guinea Time": "Папуа-Новая Гвинея Время",
	"Paraguay": "Парагвай",
	"Paraguay Time": "Парагвай Время",
	"Paramaribo": "Парамарибо",
	"Paris": "Париж",
	"Paro": "Паро",
	"Penang": "Пенанг",
	"Penza": "Пенза",
	"Perm": "Пермь",
	"Perth": "Перт",
	"Peru": "Перу",
	"Peru Time": "Перу Время",
	"Petropavlovsk-Kamchatski": "Петропавловск-Камчатский",
	"Petropavlovsk-Kamchatski Time": "Петропавловск-Камчатский Время",
	"Petrozavodsk": "Петрозаводск",
	"Philippines": "Филиппины",
	"Philippines Time": "Филиппины Время",
	"Phnom Penh": "Пномпень",
	"Phoenix Is. Time": "Феникс. Время",
	"Podgorica": "Подгорица",
	"Pohnpei": "Понпей",
	"Pohnpei Standard Time": "Pohnpei Поясному Времени",
	"Pokhara": "Покхара",
	"Poland": "Польша",
	"Pontianak": "Понтианак",
	"Port-au-Prince": "Порт-о-Пренс",
	"Portland": "Портленд",
	"Port Louis": "Порт-Луи",
	"Port Moresby": "Порт-Морсби",
	"Port of Spain": "Порт-оф-Спейн",
	"Porto Novo": "Порто-Ново",
	"Porto Velho": "Порто-Велхо",
	"Portugal": "Португалия",
	"Prague": "Прага",
	"Praia": "Прая",
	"Pretoria": "Претория",
	"Pskov": "Псков",
	"Pyongyang": "Пхеньян",
	"Qatar": "Катар",
	"Quito": "Кито",
	"Rabat": "Рабат",
	"Ramallah": "Рамалла",
	"Recife": "Ресифи",
	"Regina": "Регина",
	"Reykjavik": "Рейкъявик",
	"Riga": "Рига",
	"Rio Branco": "Риу-Бранку",
	"Rio de Janeiro": "Рио-де-Жанейро",
	"Riyadh": "Эр-Рияд",
	"Romania": "Румыния",
	"Rome": "Рим",
	"Rostov-on-Don": "Ростов-на-Дону",
	"Russia": "Россия",
	"Rwanda": "Руанда",
	"Ryazan": "Рязань",
	"Sakhalin Island time": "Время Сахалин",
	"Salekhard": "Салехард",
	"Samara": "Самара",
	"Samara Time": "Самара Время",
	"Samoa (western)": "Самоа (Западное)",
	"Sana'a": "Санаа",
	"San Francisco": "Сан-Франциско",
	"San Jose": "Сан-Хосе",
	"San Juan": "Сан-Хуан",
	"San Marino": "Сан-Марино",
	"San Salvador": "Сан-Сальвадор",
	"Santarem": "Сантарен",
	"Santiago": "Сантьяго",
	"Santo Domingo": "Санто-Доминго",
	"Sao Paulo": "Сан-Паулу",
	"Sarajevo": "Сараево",
	"Saransk": "Саранск",
	"Saratov": "Саратов",
	"Saudi Arabia": "Саудовская Аравия",
	"Scoresbysund": "Скорсбисунн",
	"Seattle": "Сиэтл",
	"Senegal": "Сенегал",
	"Seoul": "Сеул",
	"Serbia": "Сербия",
	"Seychelles": "Сейшельские о-ва",
	"Seychelles Time": "Сейшельские Острова Время",
	"Shanghai": "Шанхай",
	"Shenzhen": "Шэньчжэнь",
	"Sierra Leone": "Сьерра-Леоне",
	"Singapore": "Сингапур",
	"Singapore Time": "Сингапур Время",
	"Sitka": "Ситка",
	"Skopje": "Скопье",
	"Slovakia": "Словакия",
	"Slovenia": "Словения",
	"Smolensk": "Смоленск",
	"Sochi": "Сочи",
	"Sofia": "София",
	"Solomon Islands": "Соломоновы острова",
	"Solomon Is. Time": "Соломоновы Острова. Время",
	"Somalia": "Сомали",
	"South Africa": "Южная Африка",
	"South Africa Standard Time": "Южная Африка Поясному Времени",
	"Spain": "Испания",
	"Sri Jayewardenepura, Kotte": "Шри-Джаяварденепура-Котте",
	"Sri Lanka": "Шри-Ланка",
	"Sri Lanka Time": "Шри-Ланка Время",
	"Stavropol": "Ставрополь",
	"St. George's": "Сент-Джорджес",
	"St Helena": "Святой Елены",
	"St. John's": "Сент-Джон",
	"Stockholm": "Стокгольм",
	"St. Petersburg": "Санкт-Петербург",
	"Sucre": "Сукре",
	"Sudan": "Судан",
	"Surgut": "Сургут",
	"Suriname": "Суринам",
	"Suriname Time": "Суринам Время",
	"Suva": "Сува",
	"Swaziland": "Королевство Свазиленд",
	"Sweden": "Швеция",
	"Switzerland": "Швейцария",
	"Sydney": "Сидней",
	"Syktyvkar": "Сыктывкар",
	"Syria": "Сирия",
	"Tahiti Time": "Таити Время",
	"Taipei": "Тайбэй",
	"Taiwan": "Тайвань",
	"Tajikistan": "Таджикистан",
	"Tajikistan Time": "Таджикистан Время",
	"Tallinn": "Таллин",
	"Tambov": "Тамбов",
	"Tanzania": "Танзания",
	"Tarawa": "Тарава",
	"Tashkent": "Ташкент",
	"Tbilisi": "Тбилиси",
	"Tegucigalpa": "Тегусигальпа",
	"Tehran": "Тегеран",
	"Tel Aviv": "Тель-Авив",
	"Thailand": "Таиланд",
	"Thimphu": "Тхимпху",
	"Thunder Bay": "Тандер-Бей",
	"Tijuana": "Тихуана",
	"Tirana": "Тирана",
	"Togo": "Того",
	"Tokyo": "Токио",
	"Tomsk": "Томск",
	"Tonga": "Тонга",
	"Tonga Time": "Тонга Время",
	"Toronto": "Торонто",
	"Trinidad & Tobago": "Тринидад и Тобаго",
	"Tripoli": "Триполи",
	"Tula": "Тула",
	"Tumen": "Тюмень",
	"Tunis": "Тунис",
	"Tunisia": "Тунис",
	"Turkey": "Турция",
	"Turkmenistan": "Туркмения",
	"Turkmenistan Time": "Туркменистан Время",
	"Tuvalu": "Тувалу",
	"Tuvalu Time": "Тувалу Время",
	"Tver": "Тверь",
	"Ufa": "Уфа",
	"Uganda": "Уганда",
	"Ukraine": "Украина",
	"Ulaanbaatar": "Улан-Батор",
	"Ulaanbaatar Time": "Улан-Батор Время",
	"Ulan-Ude": "Улан-Удэ",
	"Ulyanovsk": "Ульяновск",
	"United Arab Emirates": "Объединенные Арабские Эмираты",
	"United States": "США",
	"Uruguay": "Уругвай",
	"Uruguay Time": "Уругвай Время",
	"Uzbekistan": "Узбекистан",
	"Uzbekistan Time": "Узбекистан Время",
	"Vaduz": "Вадуц",
	"Valleta": "Валетта",
	"Vancouver": "Ванкувер",
	"Vanuatu": "Вануату",
	"Vanuatu Time": "Вануату Время",
	"Vatican City": "Ватикан",
	"Venezuela": "Венесуэла",
	"Venezuela Time": "Венесуэла Время",
	"Victoria": "Виктория",
	"Vienna": "Вена",
	"Vientiane": "Вьентьян",
	"Vietnam": "Вьетнам",
	"Vila": "Вила",
	"Vilnius": "Вильнюс",
	"Vladikavkaz": "Владикавказ",
	"Vladimir": "Владимир",
	"Vladivostok": "Владивосток",
	"Vladivostok Time": "Владивосток Время",
	"Volgograd": "Волгоград",
	"Volgograd Time": "Волгоград Время",
	"Vologda": "Вологда",
	"Vorkuta": "Воркута",
	"Voronezh": "Воронеж",
	"Warsaw": "Варшава",
	"Washington D.C.": "Вашингтон",
	"Wellington": "Веллингтон",
	"West Africa Time": "Западная Африка Время",
	"Western African Time": "Western Time Африки",
	"Western European Time": "Западноевропейское Время",
	"Western Greenland Time": "Западная Гренландия Время",
	"Western Standard Time (Australia)": "Западная Поясному Времени",
	"West Samoa Time": "Западное Самоа Время",
	"Whitehorse": "Уайтхорс",
	"Windhoek": "Виндхук",
	"Winnipeg": "Виннипег",
	"Yakutat": "Якутат",
	"Yakutsk": "Якутск",
	"Yakutsk Time": "Якутск Время",
	"Yangon": "Янгон",
	"Yaounde": "Яунде",
	"Yaren": "Ярен",
	"Yaroslavl": "Ярославль",
	"Yekaterinburg": "Екатеринбург",
	"Yekaterinburg Time": "Екатеринбург Время",
	"Yellowknife": "Йеллоунайф",
	"Yemen": "Йемен",
	"Yerevan": "Ереван",
	"Yuzhno-Sakhalinsk": "Южно-Сахалинск",
	"Zagreb": "Загреб",
	"Zambia": "Замбия",
	"Zimbabwe": "Зимбабве",
	"Zurich": "Цюрих",
	"Adak": "Адак",
	"Almaty": "Алматы",
	"Aqtau": "Актау",
	"Aqtobe": "Актобе",
	"Atikokan": "Атикокан",
	"Bahia Banderas": "Баия-де-Бандерас",
	"Beulah": "Бьюла",
	"Blanc-Sablon": "Бланк-Саблон",
	"Broken Hill": "Брокен-Хилл",
	"Cambridge Bay": "Кеймбридж-Бей",
	"Canary": "Канарские о-ва",
	"Cancun": "Канкун",
	"Center": "Центр",
	"Ceuta": "Сеута",
	"Chatham": "Чатем",
	"Chokurdakh": "Chokurdakh",
	"Cocos": "Кокосовые о-ва",
	"Creston": "Крестон",
	"Currie": "Керри",
	"Dawson Creek": "Досон-Крик",
	"Easter": "Истер",
	"Enderbury": "Эндербери",
	"Gambier": "Гамбье",
	"Godthab": "Готхоб",
	"Goose Bay": "Гуз Бэй",
	"Guayaquil": "Гуаякиль",
	"Hermosillo": "Эрмосильо",
	"Indianapolis": "Индианаполис",
	"Inuvik": "Инувик",
	"Iqaluit": "Икалуит",
	"Johannesburg": "Йоханнесбург",
	"Kamchatka": "Камчатка",
	"Khandyga": "Khandyga",
	"Kiritimati": "Киритибати",
	"Knox": "Нокс",
	"Kosrae": "Кусаие",
	"Kuala Lumpur": "Куала-Лумпур",
	"Lindeman": "Линдеман",
	"Lipeck": "Липецк",
	"Lord Howe": "Лорд-Хау",
	"Louisville": "Луисвилл",
	"Maceio": "Масейо",
	"Macquarie": "Маккуори",
	"Madeira": "Мадейра",
	"Mahachkala": "Махачкала",
	"Majkop": "Майкоп",
	"Marengo": "Маренго",
	"Marquesas": "Маркизские о-ва",
	"Matamoros": "Матаморос",
	"Mazatlan": "Масатлан",
	"Merida": "Мерида",
	"Metlakatla": "Метлакатла",
	"Moncton": "Монктон",
	"Monterrey": "Монтеррей",
	"Monticello": "Мнотичелло",
	"New Salem": "Нью Сейлем",
	"Nipigon": "Нипигон",
	"Nome": "Ном",
	"Norfolk": "Норфолк",
	"Noronha": "Норонья",
	"Ojinaga": "Ojinaga",
	"Oral": "Уральск",
	"Pangnirtung": "Пангниртунг",
	"Petersburg": "Петербург",
	"Phoenix": "Феникс",
	"Qyzylorda": "Кызылорда",
	"Rainy River": "Рейни-Ривер",
	"Rankin Inlet": "Ранкин-Инлет",
	"Resolute": "Резольют",
	"Sakhalin": "Сахалин",
	"Santa Isabel": "Санта-Исабель",
	"Swift Current": "Свифт Керрент",
	"Tahiti": "Таити",
	"Tell City": "Телл Сити",
	"Thule": "о. Фула",
	"Ust-Nera": "Усть-Нера",
	"Vevay": "Vevay",
	"Vincennes": "Венсен",
	"Winamac": "Winamac",
	"Hanti-Mansijsk": "Ханты-Мансийск",
	"Абакан": "Abakan",
	"Абиджан": "Abidjan",
	"Абу-Даби": "Abu Dhabi",
	"Абуйя": "Abuja",
	"Аккра": "Accra",
	"Аддис-Абеба": "Addis Ababa",
	"Аделаида": "Adelaide",
	"Афганистан": "Afghanistan",
	"Афганистан Время": "Afghanistan Time",
	"Аляска": "Alaska",
	"Стандартное время на Аляске": "Alaska Standard Time",
	"Албания": "Albania",
	"Алжир": "Algiers",
	"Алма-Ата Время": "Alma-Ata Time",
	"Amazon Поясному Времени": "Amazon Standard Time",
	"Amazon Время (Бразилия)": "Amazon Time (Brazil)",
	"Амман": "Amman",
	"Амстердам": "Amsterdam",
	"Анадырь": "Anadyr",
	"Анадырь Время": "Anadyr Time",
	"Анкоридж": "Anchorage",
	"Андорра": "Andorra",
	"Андорра-ла-Велья": "Andorra la Vella",
	"Ангола": "Angola",
	"Анкара": "Ankara",
	"Антананариву": "Antananarivo",
	"Антигуа и Барбуда": "Antigua & Barbuda",
	"Апия": "Apia",
	"Актау Время": "Aqtau Time",
	"Актюбинская Время": "Aqtobe Time",
	"Аравия Стандартное Время": "Arabia Standard Time",
	"Арагуаяна": "Araguaina",
	"Аргентина": "Argentina",
	"Аргентина Время": "Argentina Time",
	"Аризона": "Arizona",
	"Архангельск": "Arkhangelsk",
	"Армения": "Armenia",
	"Армения Время": "Armenia Time",
	"Аруба": "Aruba",
	"Асеан Общие Времени": "ASEAN Common Time",
	"Ашхабад": "Ashkhabad",
	"Асмара": "Asmara",
	"Астана": "Astana",
	"Астрахань": "Astrakhan",
	"Асунсьон": "Asuncion",
	"Афины": "Athens",
	"Атланта": "Atlanta",
	"Атлантическое время": "Atlantic Standard Time",
	"Окленд": "Auckland",
	"Австралия": "Australia",
	"Австрия": "Austria",
	"Азербайджан": "Azerbaijan",
	"Азербайджан Время": "Azerbaijan Time",
	"Азорские о-ва": "Azores",
	"Азорские Время": "Azores Time",
	"Багдад": "Baghdad",
	"Багамские острова": "Bahamas",
	"Баия": "Bahia",
	"Бахрейн": "Bahrain",
	"Баку": "Baku",
	"Бали": "Bali",
	"Бамако": "Bamako",
	"Бандар-Сери-Бегаван": "Bandar Seri Begawan",
	"Бангалор": "Bangalore",
	"Бангкок": "Bangkok",
	"Бангладеш": "Bangladesh",
	"Бангладеш Время": "Bangladesh Time",
	"Банги": "Bangui",
	"Банджул": "Banjul",
	"Барбадос": "Barbados",
	"Барселона": "Barcelona",
	"Барнаул": "Barnaul",
	"Пекин": "Beijing",
	"Бейрут": "Beirut",
	"Белоруссия": "Belarus",
	"Белен": "Belem",
	"Бельгия": "Belgium",
	"Белгород": "Belgorod",
	"Белиз": "Belize",
	"Бельмопан": "Belmopan",
	"Бенин": "Benin",
	"Белград": "Beograd",
	"Берлин": "Berlin",
	"Бермудские о-ва": "Bermuda",
	"Берн": "Bern",
	"Бутан": "Bhutan",
	"Бутан Время": "Bhutan Time",
	"Биробиджан": "Birobidzhan",
	"Бишкек": "Bishkek",
	"Бисау": "Bissau",
	"Благовещенск": "Blagoveschensk",
	"Боа-Виста": "Boa Vista",
	"Богота": "Bogota",
	"Бойсе": "Boise",
	"Боливия": "Bolivia",
	"Боливия Время": "Bolivia Time",
	"Босния и Герцеговина": "Bosnia & Herzegovina",
	"Бостон": "Boston",
	"Ботсвана": "Botswana",
	"Бразилия": "Brazil",
	"Бразилиа Время": "Brasilia Time",
	"Братислава": "Bratislava",
	"Братск": "Bratsk",
	"Бразилия Время": "Brazil Time",
	"Браззавиль": "Brazzaville",
	"Бриджтаун": "Bridgetown",
	"Брисбен": "Brisbane",
	"Великобритания": "Britain (UK)",
	"Бруней": "Brunei",
	"Бруней Время": "Brunei Time",
	"Брюссель": "Brussels",
	"Бухарест": "Bucharest",
	"Будапешт": "Budapest",
	"Буэнос-Айрес": "Buenos Aires",
	"Бужумбура": "Bujumbura",
	"Болгария": "Bulgaria",
	"Буркина-Фасо": "Burkina Faso",
	"Бурунди": "Burundi",
	"Каир": "Cairo",
	"Калгари": "Calgary",
	"Камбоджа": "Cambodia",
	"Камерун": "Cameroon",
	"Кампу-Гранди": "Campo Grande",
	"Канада": "Canada",
	"Канберра": "Canberra",
	"Кейптаун": "Cape Town",
	"Кабо-Верде": "Cape Verde",
	"Кабо-Верде Время": "Cape Verde Time",
	"Каракас": "Caracas",
	"Касабланка": "Casablanca",
	"Центральноафриканская Республика": "Central African Rep.",
	"Центральный Время Африки": "Central African Time",
	"Central European Time": "Central European Time",
	"Центральное Время": "Central Standard Time",
	"Центральное Время (Северная Америка)": "Central Standard Time (North America)",
	"Северная Территория": "Central Standard Time (Northern Territory)",
	"Центральное Время (Южная Австралия)": "Central Standard Time (South Australia)",
	"Новый Южный Уэльс": "Eastern Standard Time (New South Wales)",
	"Центральный Западная Поясному Времени (Австралия) Неофициальный": "Central Western Standard Time (Australia) unofficial",
	"Чад": "Chad",
	"Чаморро Поясному Времени": "Chamorro Standard Time",
	"Chatham Standard Time": "Chatham Standard Time",
	"Чебоксары": "Cheboksary",
	"Челябинск": "Chelyabinsk",
	"Черкесск": "Cherkessk",
	"Чианг-Май": "Chiang Mai",
	"Чикаго": "Chicago",
	"Чиуауа": "Chihuahua",
	"Чили": "Chile",
	"Чили Время": "Chile Time",
	"Китай": "China",
	"Китай Поясному Времени": "China Standard Time",
	"Чита": "Chita",
	"Читтагонг": "Chittagong",
	"Чойбалсан": "Choibalsan",
	"Рождество": "Christmas",
	"Остров Рождества": "Christmas Island",
	"Остров Рождества Время": "Christmas Island Time",
	"Чуук": "Chuuk",
	"Chuuk Время": "Chuuk Time",
	"Кокосовые Острова Время": "Cocos Islands Time",
	"Колумбия": "Colombia",
	"Колумбия Время": "Colombia Time",
	"Коломбо": "Colombo",
	"Коморские острова": "Comoros",
	"Конакри": "Conakry",
	"Конго (Дем. Респ.)": "Congo (Dem. Rep.)",
	"Конго (Респ.)": "Congo (Rep.)",
	"Копенгаген": "Copenhagen",
	"Коста-Рика": "Costa Rica",
	"Cote d'Ivoire": "Cote d'Ivoire",
	"Хорватия": "Croatia",
	"Куба": "Cuba",
	"Куяба": "Cuiaba",
	"Кипр": "Cyprus",
	"Чехия": "Czech Republic",
	"Дакар": "Dakar",
	"Даллас": "Dallas",
	"Дамасск": "Damascus",
	"Датская гавань": "Danmarkshavn",
	"Дар-Эс-Салам": "Dar es Salaam",
	"Дарвин": "Darwin",
	"Доусон": "Dawson",
	"Дания": "Denmark",
	"Денвер": "Denver",
	"Детройт": "Detroit",
	"Дакка": "Dhaka",
	"Джибути": "Djibouti",
	"Доха": "Doha",
	"Доминиканская Республика": "Dominican Republic",
	"Дубаи": "Dubai",
	"Дублин": "Dublin",
	"Дудинка": "Dudinka",
	"Душанбе": "Dushanbe",
	"Восточная Африка Время": "East Africa Time",
	"Пасха. Время": "Easter Is. Time",
	"Восточной Африки Время": "Eastern African Time",
	"Восточноевропейское Время": "Eastern European Time",
	"Восточная Гренландия Время": "Eastern Greenland Time",
	"Eastern Standard Time": "Eastern Standard Time",
	"Eastern Standard Time (Австралия)": "Eastern Standard Time (Australia)",
	"Eastern Standard Time (Северная Америка)": "Eastern Standard Time (North America)",
	"Квинсленд": "Eastern Standard Time (Queensland)",
	"Тасмания": "Eastern Standard Time (Tasmania)",
	"Эквадор": "Ecuador",
	"Эквадор Время": "Ecuador Time",
	"Эдинбург": "Edinburgh",
	"Edmonton": "Edmonton",
	"Египет": "Egypt",
	"Эйрунепе": "Eirunepe",
	"Екатеринбург": "Yekaterinburg",
	"Элиста": "Elista",
	"Эль-Сальвадор": "El Salvador",
	"Экваториальная Гвинея": "Equatorial Guinea",
	"Эритрея": "Eritrea",
	"Эстония": "Estonia",
	"Эфиопия": "Ethiopia",
	"Еукла": "Eucla",
	"Фернандо Де Норонья Время": "Fernando de Noronha Time",
	"Фиджи": "Fiji",
	"Фиджи Время": "Fiji Time",
	"Финляндия": "Finland",
	"Форталеза": "Fortaleza",
	"Франция": "France",
	"Франкфурт": "Frankfurt",
	"Фритаун": "Freetown",
	"Фунафути": "Funafuti",
	"Габон": "Gabon",
	"Габороне": "Gaborone",
	"Галапагос": "Galapagos",
	"Галапагосские Время": "Galapagos Time",
	"Гамбия": "Gambia",
	"Гамбиер Время": "Gambier Time",
	"Джорджтаун": "Georgetown",
	"Грузия": "Georgia",
	"Грузия Время": "Georgia Time",
	"Германия": "Germany",
	"Гана": "Ghana",
	"Гилберт. Время": "Gilbert Is. Time",
	"Глейс-Бей": "Glace Bay",
	"Горно-Алтайск": "Gorno-Altaysk",
	"Греция": "Greece",
	"Гренландия": "Greenland",
	"Время по Гринвичу": "Greenwich Mean Time",
	"Гренада": "Grenada",
	"Грозный": "Grozny",
	"Гуам": "Guam",
	"Гуанчжоу": "Guangzhou",
	"Гватемала": "Guatemala City",
	"Гуаякиль": "Guayaquil",
	"Гвинея": "Guinea",
	"Гвинея Бисау": "Guinea-Bissau",
	"Gulf Стандартное Время": "Gulf Standard Time",
	"Гайана": "Guyana",
	"Гайана Время": "Guyana Time",
	"Гаити": "Haiti",
	"Галифакс": "Halifax",
	"Hamburg": "Hamburg",
	"Гамильтон": "Hamilton",
	"Ханой": "Hanoi",
	"Хараре": "Harare",
	"Гавайи": "Hawaii",
	"Гавайи-Алеутской Поясному Времени": "Hawaii-Aleutian Standard Time",
	"Гавайи Поясному Времени": "Hawaii Standard Time",
	"Хельсинки": "Helsinki",
	"Хобарт": "Hobart",
	"Хошимин": "Ho Chi Minh City",
	"Гондурас": "Honduras",
	"Гонконг": "Hong Kong",
	"Время в Гонконге": "Hong Kong Time",
	"Хониара": "Honiara",
	"Гонолулу": "Honolulu",
	"Хьюстон": "Houston",
	"Ховд": "Hovd",
	"Венгрия": "Hungary",
	"Исландия": "Iceland",
	"Индия": "India",
	"Индийский Поясному Времени": "Indian Standard Time",
	"Индокитай Время": "Indochina Time",
	"Индонезия": "Indonesia",
	"Йошкар-Ола": "Ioshkar Ola",
	"Иран": "Iran",
	"Иран Время": "Iran Time",
	"Ирак": "Iraq",
	"Ирландия": "Ireland",
	"Иркутск": "Irkutsk",
	"Иркутск Время": "Irkutsk Time",
	"Исламабад": "Islamabad",
	"Израиль": "Israel",
	"Израильское Время": "Israel Standard Time",
	"Стамбул": "Istanbul",
	"Италия": "Italy",
	"Иваново": "Ivanovo",
	"Ижевск": "Izhevsk",
	"Джакарта": "Jakarta",
	"Ямайка": "Jamaica",
	"Джеймстаун": "James Town",
	"Япония": "Japan",
	"Япония Поясному Времени": "Japan Standard Time",
	"Java Время": "Java Time",
	"Яяпура": "Jayapura",
	"Джаяпура Время": "Jayapura Time",
	"Джедда": "Jeddah",
	"Иерусалим": "Jerusalem",
	"Йоханнесбург": "Johannesburg",
	"Иордания": "Jordan",
	"Джуно": "Juneau",
	"Кабул": "Kabul",
	"Калининград": "Kaliningrad",
	"Калуга": "Kaluga",
	"Кампала": "Kampala",
	"Карачи": "Karachi",
	"Катманду": "Kathmandu",
	"Казахстан": "Kazakhstan",
	"Казань": "Kazan",
	"Кемерово": "Kemerovo",
	"Кения": "Kenya",
	"Хартум": "Khartoum",
	"Khovd Время": "Khovd Time",
	"Киев": "Kiev",
	"Кигали": "Kigali",
	"Кингстон": "Kingston",
	"Киншаса": "Kinshasa",
	"Кыргызстан Время": "Kirgizstan Time",
	"Кирибати": "Kiribati",
	"Киров": "kirov",
	"Кишинев": "Kishinev",
	"Комсомольск-на-Амуре": "Komsomolsk-on-Amur",
	"Корея (Северная)": "Korea (North)",
	"Корея (Южная)": "Korea (South)",
	"Корея Поясному Времени": "Korea Standard Time",
	"Корор": "Koror",
	"Kosrae Время": "Kosrae Time",
	"Краснодар": "Krasnodar",
	"Красноярск": "Krasnoyarsk",
	"Красноярск Время": "Krasnoyarsk Time",
	"Куала-Лумпур": "Kuala Lumpur",
	"Курган": "Kurgan",
	"Курск": "Kursk",
	"Кувейт": "Kuwait City",
	"Киргизия": "Kyrgyzstan",
	"Кызыл": "Kyzyl",
	"Гавана": "La Habana",
	"Лаос": "Laos",
	"Ла-Пас": "La Paz",
	"Лас-Вегас": "Las Vegas",
	"Латвия": "Latvia",
	"Ливан": "Lebanon",
	"Лесото": "Lesotho",
	"Либерия": "Liberia",
	"Либрвиль": "Libreville",
	"Ливия": "Libya",
	"Лихтенштейн": "Liechtenstein",
	"Лилонгве": "Lilongwe",
	"Лима": "Lima",
	"Линия. Время": "Line Is. Time",
	"Лиссабон": "Lisbon",
	"Литва": "Lithuania",
	"Любляна": "Ljubljana",
	"Загрузите Хау Стандартное Время": "Load Howe Standard Time",
	"Ломе": "Lome",
	"Лондон": "London",
	"Лос-Анджелес": "Los Angeles",
	"Луанда": "Luanda",
	"Лусака": "Lusaka",
	"Люксембург": "Luxemburg",
	"Лусон": "Luzon",
	"Макао": "Macao",
	"Macau": "Macau",
	"Македония": "Macedonia",
	"Остров Маккуори Станция Время": "Macquarie Island Station Time",
	"Мадагаскар": "Madagascar",
	"Мадрид": "Madrid",
	"Магадан": "Magadan",
	"Магадан Время": "Magadan Time",
	"Маджуро": "Majuro",
	"Макасар": "Makassar",
	"Малабо": "Malabo",
	"Малави": "Malawi",
	"Малайзия": "Malaysia",
	"Малайзия Время": "Malaysia Time",
	"Мальдивы": "Maldives",
	"Мальдивские О-Ва Время": "Maldives Time",
	"Мале": "Male",
	"Мали": "Mali",
	"Мальта": "Malta",
	"Манагуа": "Managua",
	"Манама": "Manama",
	"Манаус": "Manaus",
	"Мандалай": "Mandalay",
	"Манила": "Manila",
	"Мапуто": "Maputo",
	"Маркизские Время": "Marquesas Time",
	"Маршалловы о-ва": "Marshall Islands",
	"Маршалловы Острова Время": "Marshall Islands Time",
	"Масеру": "Maseru",
	"Мавритания": "Mauritania",
	"Маврикий": "Mauritius",
	"Маврикий Время": "Mauritius Time",
	"Мбабане": "Mbabane",
	"Мельбурн": "Melbourne",
	"Меномини": "Menominee",
	"MeST": "MeST",
	"Мексика": "Mexico",
	"Мехико": "Mexico City",
	"Микронезия": "Micronesia",
	"Милан": "Milano",
	"Минск": "Minsk",
	"Могадишу": "Mogadishu",
	"Молдова": "Moldova",
	"Монако": "Monaco",
	"Монголия": "Mongolia",
	"Монровия": "Monrovia",
	"Черногория": "Montenegro",
	"Монтевидео": "Montevideo",
	"Монреаль": "Montreal",
	"Марокко": "Morocco",
	"Морони": "Moroni",
	"Москва": "Moscow",
	"Москва Поясному Времени": "Moscow Standard Time",
	"Горное Время": "Mountain Standard Time",
	"Горное Время (Северная Америка)": "Mountain Standard Time (North America)",
	"Мозамбик": "Mozambique",
	"Мумбаи": "Mumbai",
	"Мюнхен": "Munich",
	"Мурманск": "Murmansk",
	"Мускат": "Muscat",
	"Мьянма (Бирма)": "Myanmar (Burma)",
	"Мьянма Время": "Myanmar Time",
	"Найроби": "Nairobi",
	"Нальчик": "Nalchik",
	"Намибия": "Namibia",
	"Неаполь": "Napoli",
	"Нарьян-Мар": "Naryan-Mar",
	"Нассау": "Nassau",
	"Науру": "Nauru",
	"Науру Время": "Nauru Time",
	"Нджамена": "N'Djamena",
	"Непал": "Nepal",
	"Непал Время": "Nepal Time",
	"Нидерланды": "Netherlands",
	"Новая Каледония": "New Caledonia",
	"Новая Каледония Время": "New Caledonia Time",
	"Дели": "New Delhi",
	"Ньюфаундленд Поясному Времени": "Newfoundland Standard Time",
	"Нью-Йорк": "New York",
	"Новая Зеландия": "New Zealand",
	"Новая Зеландия Поясному Времени": "New Zealand Standard Time",
	"Ниамей": "Niamey",
	"Никарагуа": "Nicaragua",
	"Никосия": "Nicosia",
	"Нигер": "Niger",
	"Нигерия": "Nigeria",
	"Нижний Новгород": "Nizhni Novgorod",
	"Остров Норфолк": "Norfolk Island",
	"Норфолк Время": "Norfolk Time",
	"Норильск": "Norilsk",
	"Норвегия": "Norway",
	"Нуакшот": "Nouakchott",
	"Новгород": "Novgorod",
	"Новокузнецк": "Novokuznetsk",
	"Новосибирск": "Novosibirsk",
	"Новосибирск Время": "Novosibirsk Time",
	"Нукуалофа": "Nukualofa",
	"Оман": "Oman",
	"Омск": "Omsk",
	"Омск Время": "Omsk Time",
	"Время Оральный": "Oral Time",
	"Ораньестад": "Oranjestad",
	"Орел": "Orel",
	"Оренбург": "Orenburg",
	"Osaka": "Osaka",
	"Осло": "Oslo",
	"Оттава": "Ottawa",
	"Уагадугу": "Ouagadougou",
	"Стандартное тихоокеанское время": "Pacific Standard Time",
	"Стандартное тихоокеанское время (Северная Америка)": "Pacific Standard Time (North America)",
	"Пакистан": "Pakistan",
	"Пакистан Время": "Pakistan Time",
	"Палау": "Palau",
	"Palau Время": "Palau Time",
	"Палестина": "Palestine",
	"Паликир": "Palikir",
	"Панама": "Panama City",
	"Папуа": "Papua",
	"Папуа - Новая Гвинея": "Papua New Guinea",
	"Папуа-Новая Гвинея Время": "Papua New Guinea Time",
	"Парагвай": "Paraguay",
	"Парагвай Время": "Paraguay Time",
	"Парамарибо": "Paramaribo",
	"Париж": "Paris",
	"Паро": "Paro",
	"Пенанг": "Penang",
	"Пенза": "Penza",
	"Пермь": "Perm",
	"Перт": "Perth",
	"Перу": "Peru",
	"Перу Время": "Peru Time",
	"Петропавловск-Камчатский": "Petropavlovsk-Kamchatski",
	"Петропавловск-Камчатский Время": "Petropavlovsk-Kamchatski Time",
	"Петрозаводск": "Petrozavodsk",
	"Филиппины": "Philippines",
	"Филиппины Время": "Philippines Time",
	"Пномпень": "Phnom Penh",
	"Феникс. Время": "Phoenix Is. Time",
	"Подгорица": "Podgorica",
	"Понпей": "Pohnpei",
	"Pohnpei Поясному Времени": "Pohnpei Standard Time",
	"Покхара": "Pokhara",
	"Польша": "Poland",
	"Понтианак": "Pontianak",
	"Порт-о-Пренс": "Port-au-Prince",
	"Портленд": "Portland",
	"Порт-Луи": "Port Louis",
	"Порт-Морсби": "Port Moresby",
	"Порт-оф-Спейн": "Port of Spain",
	"Порто-Ново": "Porto Novo",
	"Порто-Велхо": "Porto Velho",
	"Португалия": "Portugal",
	"Прага": "Prague",
	"Прая": "Praia",
	"Претория": "Pretoria",
	"Псков": "Pskov",
	"Пхеньян": "Pyongyang",
	"Катар": "Qatar",
	"Кито": "Quito",
	"Рабат": "Rabat",
	"Рамалла": "Ramallah",
	"Ресифи": "Recife",
	"Регина": "Regina",
	"Рейкъявик": "Reykjavik",
	"Рига": "Riga",
	"Риу-Бранку": "Rio Branco",
	"Рио-де-Жанейро": "Rio de Janeiro",
	"Эр-Рияд": "Riyadh",
	"Румыния": "Romania",
	"Рим": "Rome",
	"Ростов-на-Дону": "Rostov-on-Don",
	"Россия": "Russia",
	"Руанда": "Rwanda",
	"Рязань": "Ryazan",
	"Время Сахалин": "Sakhalin Island time",
	"Салехард": "Salekhard",
	"Самара": "Samara",
	"Самара Время": "Samara Time",
	"Самоа (Западное)": "Samoa (western)",
	"Санаа": "Sana'a",
	"Сан-Франциско": "San Francisco",
	"Сан-Хосе": "San Jose",
	"Сан-Хуан": "San Juan",
	"Сан-Марино": "San Marino",
	"Сан-Сальвадор": "San Salvador",
	"Сантарен": "Santarem",
	"Сантьяго": "Santiago",
	"Санто-Доминго": "Santo Domingo",
	"Сан-Паулу": "Sao Paulo",
	"Сараево": "Sarajevo",
	"Саранск": "Saransk",
	"Саратов": "Saratov",
	"Саудовская Аравия": "Saudi Arabia",
	"Скорсбисунн": "Scoresbysund",
	"Сиэтл": "Seattle",
	"Сенегал": "Senegal",
	"Сеул": "Seoul",
	"Сербия": "Serbia",
	"Сейшельские о-ва": "Seychelles",
	"Сейшельские Острова Время": "Seychelles Time",
	"Шанхай": "Shanghai",
	"Шэньчжэнь": "Shenzhen",
	"Сьерра-Леоне": "Sierra Leone",
	"Сингапур": "Singapore",
	"Сингапур Время": "Singapore Time",
	"Ситка": "Sitka",
	"Скопье": "Skopje",
	"Словакия": "Slovakia",
	"Словения": "Slovenia",
	"Смоленск": "Smolensk",
	"Сочи": "Sochi",
	"София": "Sofia",
	"Соломоновы острова": "Solomon Islands",
	"Соломоновы Острова. Время": "Solomon Is. Time",
	"Сомали": "Somalia",
	"Южная Африка": "South Africa",
	"Южная Африка Поясному Времени": "South Africa Standard Time",
	"Испания": "Spain",
	"Шри-Джаяварденепура-Котте": "Sri Jayewardenepura, Kotte",
	"Шри-Ланка": "Sri Lanka",
	"Шри-Ланка Время": "Sri Lanka Time",
	"Ставрополь": "Stavropol",
	"Сент-Джорджес": "St. George's",
	"Святой Елены": "St Helena",
	"Сент-Джон": "St. John's",
	"Стокгольм": "Stockholm",
	"Санкт-Петербург": "St. Petersburg",
	"Сукре": "Sucre",
	"Судан": "Sudan",
	"Сургут": "Surgut",
	"Суринам": "Suriname",
	"Суринам Время": "Suriname Time",
	"Сува": "Suva",
	"Королевство Свазиленд": "Swaziland",
	"Швеция": "Sweden",
	"Швейцария": "Switzerland",
	"Сидней": "Sydney",
	"Сыктывкар": "Syktyvkar",
	"Сирия": "Syria",
	"Таити Время": "Tahiti Time",
	"Тайбэй": "Taipei",
	"Тайвань": "Taiwan",
	"Таджикистан": "Tajikistan",
	"Таджикистан Время": "Tajikistan Time",
	"Таллин": "Tallinn",
	"Тамбов": "Tambov",
	"Танзания": "Tanzania",
	"Тарава": "Tarawa",
	"Ташкент": "Tashkent",
	"Тбилиси": "Tbilisi",
	"Тегусигальпа": "Tegucigalpa",
	"Тегеран": "Tehran",
	"Тель-Авив": "Tel Aviv",
	"Таиланд": "Thailand",
	"Тхимпху": "Thimphu",
	"Тандер-Бей": "Thunder Bay",
	"Тихуана": "Tijuana",
	"Тирана": "Tirana",
	"Того": "Togo",
	"Токио": "Tokyo",
	"Томск": "Tomsk",
	"Тонга": "Tonga",
	"Тонга Время": "Tonga Time",
	"Торонто": "Toronto",
	"Тринидад и Тобаго": "Trinidad & Tobago",
	"Триполи": "Tripoli",
	"Тула": "Tula",
	"Тюмень": "Tumen",
	"Тунис": "Tunisia",
	"Турция": "Turkey",
	"Туркмения": "Turkmenistan",
	"Туркменистан Время": "Turkmenistan Time",
	"Тувалу": "Tuvalu",
	"Тувалу Время": "Tuvalu Time",
	"Тверь": "Tver",
	"Уфа": "Ufa",
	"Уганда": "Uganda",
	"Украина": "Ukraine",
	"Улан-Батор": "Ulaanbaatar",
	"Улан-Батор Время": "Ulaanbaatar Time",
	"Улан-Удэ": "Ulan-Ude",
	"Ульяновск": "Ulyanovsk",
	"Объединенные Арабские Эмираты": "United Arab Emirates",
	"США": "United States",
	"Уругвай": "Uruguay",
	"Уругвай Время": "Uruguay Time",
	"Узбекистан": "Uzbekistan",
	"Узбекистан Время": "Uzbekistan Time",
	"Вадуц": "Vaduz",
	"Валетта": "Valleta",
	"Ванкувер": "Vancouver",
	"Вануату": "Vanuatu",
	"Вануату Время": "Vanuatu Time",
	"Ватикан": "Vatican City",
	"Венесуэла": "Venezuela",
	"Венесуэла Время": "Venezuela Time",
	"Виктория": "Victoria",
	"Вена": "Vienna",
	"Вьентьян": "Vientiane",
	"Вьетнам": "Vietnam",
	"Вила": "Vila",
	"Вильнюс": "Vilnius",
	"Владикавказ": "Vladikavkaz",
	"Владимир": "Vladimir",
	"Владивосток": "Vladivostok",
	"Владивосток Время": "Vladivostok Time",
	"Волгоград": "Volgograd",
	"Волгоград Время": "Volgograd Time",
	"Вологда": "Vologda",
	"Воркута": "Vorkuta",
	"Воронеж": "Voronezh",
	"Варшава": "Warsaw",
	"Вашингтон": "Washington D.C.",
	"Веллингтон": "Wellington",
	"Западная Африка Время": "West Africa Time",
	"Western Time Африки": "Western African Time",
	"Западноевропейское Время": "Western European Time",
	"Западная Гренландия Время": "Western Greenland Time",
	"Западная Поясному Времени": "Western Standard Time (Australia)",
	"Западное Самоа Время": "West Samoa Time",
	"Уайтхорс": "Whitehorse",
	"Виндхук": "Windhoek",
	"Виннипег": "Winnipeg",
	"Якутат": "Yakutat",
	"Якутск": "Yakutsk",
	"Якутск Время": "Yakutsk Time",
	"Янгон": "Yangon",
	"Яунде": "Yaounde",
	"Ярен": "Yaren",
	"Ярославль": "Yaroslavl",
	"Екатеринбург Время": "Yekaterinburg Time",
	"Йеллоунайф": "Yellowknife",
	"Йемен": "Yemen",
	"Ереван": "Yerevan",
	"Южно-Сахалинск": "Yuzhno-Sakhalinsk",
	"Загреб": "Zagreb",
	"Замбия": "Zambia",
	"Зимбабве": "Zimbabwe",
	"Цюрих": "Zurich",
	"Адак": "Adak",
	"Алматы": "Almaty",
	"Актау": "Aqtau",
	"Актобе": "Aqtobe",
	"Атикокан": "Atikokan",
	"Баия-де-Бандерас": "Bahia Banderas",
	"Бьюла": "Beulah",
	"Бланк-Саблон": "Blanc-Sablon",
	"Брокен-Хилл": "Broken Hill",
	"Кеймбридж-Бей": "Cambridge Bay",
	"Канарские о-ва": "Canary",
	"Канкун": "Cancun",
	"Центр": "Center",
	"Сеута": "Ceuta",
	"Чатем": "Chatham",
	"Chokurdakh": "Chokurdakh",
	"Кокосовые о-ва": "Cocos",
	"Крестон": "Creston",
	"Керри": "Currie",
	"Досон-Крик": "Dawson Creek",
	"Истер": "Easter",
	"Эндербери": "Enderbury",
	"Гамбье": "Gambier",
	"Готхоб": "Godthab",
	"Гуз Бэй": "Goose Bay",
	"Эрмосильо": "Hermosillo",
	"Индианаполис": "Indianapolis",
	"Инувик": "Inuvik",
	"Икалуит": "Iqaluit",
	"Камчатка": "Kamchatka",
	"Khandyga": "Khandyga",
	"Киритибати": "Kiritimati",
	"Нокс": "Knox",
	"Кусаие": "Kosrae",
	"Линдеман": "Lindeman",
	"Липецк": "Lipeck",
	"Лорд-Хау": "Lord Howe",
	"Луисвилл": "Louisville",
	"Масейо": "Maceio",
	"Маккуори": "Macquarie",
	"Мадейра": "Madeira",
	"Махачкала": "Mahachkala",
	"Майкоп": "Majkop",
	"Маренго": "Marengo",
	"Маркизские о-ва": "Marquesas",
	"Матаморос": "Matamoros",
	"Масатлан": "Mazatlan",
	"Мерида": "Merida",
	"Метлакатла": "Metlakatla",
	"Монктон": "Moncton",
	"Монтеррей": "Monterrey",
	"Мнотичелло": "Monticello",
	"Нью Сейлем": "New Salem",
	"Нипигон": "Nipigon",
	"Ном": "Nome",
	"Норфолк": "Norfolk",
	"Норонья": "Noronha",
	"Ojinaga": "Ojinaga",
	"Уральск": "Oral",
	"Пангниртунг": "Pangnirtung",
	"Петербург": "Petersburg",
	"Феникс": "Phoenix",
	"Кызылорда": "Qyzylorda",
	"Рейни-Ривер": "Rainy River",
	"Ранкин-Инлет": "Rankin Inlet",
	"Резольют": "Resolute",
	"Сахалин": "Sakhalin",
	"Санта-Исабель": "Santa Isabel",
	"Свифт Керрент": "Swift Current",
	"Таити": "Tahiti",
	"Телл Сити": "Tell City",
	"о. Фула": "Thule",
	"Усть-Нера": "Ust-Nera",
	"Vevay": "Vevay",
	"Венсен": "Vincennes",
	"Winamac": "Winamac",
	"Ханты-Мансийск": "Hanti-Mansijsk"
}